[
  {
    "genero":"Action",
    "popularidad":33.1534006291,
    "proporcion":16.3041596954,
    "residuos":16.8492409337
  },
  {
    "genero":"Demons",
    "popularidad":21.6956336179,
    "proporcion":17.3743725841,
    "residuos":4.3212610338
  },
  {
    "genero":"Comedy",
    "popularidad":17.1081299891,
    "proporcion":8.9338256505,
    "residuos":8.1743043386
  },
  {
    "genero":"Adventure",
    "popularidad":15.3070860319,
    "proporcion":12.7415911844,
    "residuos":2.5654948474
  },
  {
    "genero":"Music",
    "popularidad":10.1578563929,
    "proporcion":9.9607684763,
    "residuos":0.1970879165
  },
  {
    "genero":"Kids",
    "popularidad":1.889067679,
    "proporcion":14.7406680898,
    "residuos":-12.8516004108
  },
  {
    "genero":"Harem",
    "popularidad":0.6888256602,
    "proporcion":19.9446143195,
    "residuos":-19.2557886593
  }
]